reseval/__init__.py
reseval/pipelines.py
resident_eval-0.0.0.dist-info/METADATA
resident_eval-0.0.0.dist-info/WHEEL
resident_eval-0.0.0.dist-info/top_level.txt
resident_eval-0.0.0.dist-info/RECORD
